upowwalletpy/__init__.py
upowwalletpy/push.py
upowwalletpy/upow_transactions/__init__.py
upowwalletpy/upow_transactions/coinbase_transaction.py
upowwalletpy/upow_transactions/constants.py
upowwalletpy/upow_transactions/helpers.py
upowwalletpy/upow_transactions/transaction.py
upowwalletpy/upow_transactions/transaction_input.py
upowwalletpy/upow_transactions/transaction_output.py
upowwalletpy/utils/__init__.py
upowwalletpy/utils/repository.py
upowwalletpy/utils/utils.py
upowwalletpy-1.0.2.dist-info/METADATA
upowwalletpy-1.0.2.dist-info/WHEEL
upowwalletpy-1.0.2.dist-info/top_level.txt
upowwalletpy-1.0.2.dist-info/RECORD
