Metadata-Version: 2.1
Name: upowwalletpy
Version: 1.0.2
Summary: A package for UPOW wallet transactions
Author: upow
Author-email: contact@upow.ai
Requires-Python: >=3.11
Requires-Dist: asttokens ==2.4.1
Requires-Dist: base58 ==0.2.5
Requires-Dist: certifi ==2023.11.17
Requires-Dist: charset-normalizer ==2.0.12
Requires-Dist: colorama ==0.4.6
Requires-Dist: executing ==2.0.1
Requires-Dist: fastecdsa ==2.3.0
Requires-Dist: icecream ==2.1.3
Requires-Dist: idna ==3.6
Requires-Dist: pygments ==2.17.2
Requires-Dist: requests ==2.26.0
Requires-Dist: six ==1.16.0
Requires-Dist: urllib3 ==1.26.18
Requires-Dist: pickleDB ~=0.9.2
